hospital/__init__.py
hospital/admin.py
hospital/apps.py
hospital/doctor.py
hospital/lillnes.py
hospital/medicines.py
hospital/models.py
hospital/pations.py
hospital/rooms.py
hospital/staff.py
hospital/tests.py
hospital/urls.py
hospital/views.py
hospital/migrations/0001_initial.py
hospital/migrations/__init__.py
my_library_hospital_management-0.1.dist-info/METADATA
my_library_hospital_management-0.1.dist-info/WHEEL
my_library_hospital_management-0.1.dist-info/top_level.txt
my_library_hospital_management-0.1.dist-info/RECORD
