Metadata-Version: 2.1
Name: my_library_hospital_management
Version: 0.1
Summary: Hospital Management
Classifier: Programming Language :: Python :: 3
Classifier: Operating System :: OS Independent
Requires-Dist: asgiref
Requires-Dist: Django
Requires-Dist: parse
Requires-Dist: Pillow
Requires-Dist: sqlparse
Requires-Dist: tzdata
